<?xml version="1.0"?>
<libraries>
    <library>
        <location>mod/iadlearning/amd/src/buttons.bootstrap.js</location>
        <name>DataTables</name>
        <license>MIT</license>
        <version>1.10.9</version>
    </library>
    <library>
        <location>mod/iadlearning/amd/src/dataTables.bootstrap.js</location>
        <name>DataTables</name>
        <license>MIT</license>
        <version>1.10.9</version>
    </library>
    <library>
        <location>mod/iadlearning/amd/src/dataTables.buttons.js</location>
        <name>DataTables</name>
        <license>MIT</license>
        <version>1.10.9</version>
    </library>
    <library>
        <location>mod/iadlearning/amd/src/dataTables.select.js</location>
        <name>DataTables</name>
        <license>MIT</license>
        <version>1.10.9</version>
    </library>
    <library>
        <location>mod/iadlearning/amd/src/jquery.dataTables.js</location>
        <name>DataTables</name>
        <license>MIT</license>
        <version>1.10.9</version>
    </library>
</libraries>
